<?xml version="1.0"?><content>
<ANIMAL>
	<nrOfLegs>4</nrOfLegs>
	<name>Lizard</name>
	<maintenanceCost>3.3</maintenanceCost>
	<dangerPerc>0.01</dangerPerc>
	<takenCareOf>false</takenCareOf>
	<layEggs>true</layEggs>
	<DISCRIMINANT>LIZARD</DISCRIMINANT>
</ANIMAL>
<ANIMAL>
	<nrOfLegs>8</nrOfLegs>
	<name>Spider</name>
	<maintenanceCost>2.1</maintenanceCost>
	<dangerPerc>0.5</dangerPerc>
	<takenCareOf>false</takenCareOf>
	<canFly>false</canFly>
	<isDangerous>true</isDangerous>
	<DISCRIMINANT>SPIDER</DISCRIMINANT>
</ANIMAL>
<ANIMAL>
	<nrOfLegs>2</nrOfLegs>
	<name>Chicken</name>
	<maintenanceCost>2.1</maintenanceCost>
	<dangerPerc>0.0</dangerPerc>
	<takenCareOf>false</takenCareOf>
	<migrates>true</migrates>
	<avgFlightAltitude>0</avgFlightAltitude>
	<DISCRIMINANT>CHICKEN</DISCRIMINANT>
</ANIMAL>
<ANIMAL>
	<nrOfLegs>6</nrOfLegs>
	<name>Cockroach</name>
	<maintenanceCost>0.5</maintenanceCost>
	<dangerPerc>0.0</dangerPerc>
	<takenCareOf>false</takenCareOf>
	<canFly>false</canFly>
	<isDangerous>false</isDangerous>
	<DISCRIMINANT>COCKROACH</DISCRIMINANT>
</ANIMAL>
<ANIMAL>
	<nrOfLegs>2</nrOfLegs>
	<name>Monkey</name>
	<maintenanceCost>6.3</maintenanceCost>
	<dangerPerc>0.21</dangerPerc>
	<takenCareOf>false</takenCareOf>
	<normalBodyTemp>37.2</normalBodyTemp>
	<percBodyHair>88.1</percBodyHair>
	<DISCRIMINANT>MONKEY</DISCRIMINANT>
</ANIMAL>
<ANIMAL>
	<nrOfLegs>4</nrOfLegs>
	<name>Turtle</name>
	<maintenanceCost>3.9</maintenanceCost>
	<dangerPerc>0.0</dangerPerc>
	<takenCareOf>false</takenCareOf>
	<layEggs>true</layEggs>
	<DISCRIMINANT>TURTLE</DISCRIMINANT>
</ANIMAL>
<ANIMAL>
	<nrOfLegs>6</nrOfLegs>
	<name>Cockroach</name>
	<maintenanceCost>0.5</maintenanceCost>
	<dangerPerc>0.0</dangerPerc>
	<takenCareOf>false</takenCareOf>
	<canFly>false</canFly>
	<isDangerous>false</isDangerous>
	<DISCRIMINANT>COCKROACH</DISCRIMINANT>
</ANIMAL>
<ANIMAL>
	<nrOfLegs>2</nrOfLegs>
	<name>Owl</name>
	<maintenanceCost>3.6</maintenanceCost>
	<dangerPerc>0.0</dangerPerc>
	<takenCareOf>false</takenCareOf>
	<migrates>false</migrates>
	<avgFlightAltitude>2000</avgFlightAltitude>
	<DISCRIMINANT>OWL</DISCRIMINANT>
</ANIMAL>
<ANIMAL>
	<nrOfLegs>4</nrOfLegs>
	<name>Lizard</name>
	<maintenanceCost>3.3</maintenanceCost>
	<dangerPerc>0.01</dangerPerc>
	<takenCareOf>false</takenCareOf>
	<layEggs>true</layEggs>
	<DISCRIMINANT>LIZARD</DISCRIMINANT>
</ANIMAL>
<ANIMAL>
	<nrOfLegs>4</nrOfLegs>
	<name>Tiger</name>
	<maintenanceCost>6.3</maintenanceCost>
	<dangerPerc>0.65</dangerPerc>
	<takenCareOf>false</takenCareOf>
	<normalBodyTemp>37.0</normalBodyTemp>
	<percBodyHair>95.3</percBodyHair>
	<DISCRIMINANT>TIGER</DISCRIMINANT>
</ANIMAL>
<ANIMAL>
	<nrOfLegs>4</nrOfLegs>
	<name>Turtle</name>
	<maintenanceCost>3.9</maintenanceCost>
	<dangerPerc>0.0</dangerPerc>
	<takenCareOf>false</takenCareOf>
	<layEggs>true</layEggs>
	<DISCRIMINANT>TURTLE</DISCRIMINANT>
</ANIMAL>
<ANIMAL>
	<nrOfLegs>0</nrOfLegs>
	<name>Shark</name>
	<maintenanceCost>5.2</maintenanceCost>
	<dangerPerc>0.75</dangerPerc>
	<takenCareOf>false</takenCareOf>
	<avgSwimDepth>2000</avgSwimDepth>
	<waterType>SALTWATER</waterType>
	<DISCRIMINANT>SHARK</DISCRIMINANT>
</ANIMAL>
<ANIMAL>
	<nrOfLegs>4</nrOfLegs>
	<name>Tiger</name>
	<maintenanceCost>6.3</maintenanceCost>
	<dangerPerc>0.65</dangerPerc>
	<takenCareOf>false</takenCareOf>
	<normalBodyTemp>37.0</normalBodyTemp>
	<percBodyHair>95.3</percBodyHair>
	<DISCRIMINANT>TIGER</DISCRIMINANT>
</ANIMAL>
<ANIMAL>
	<nrOfLegs>6</nrOfLegs>
	<name>Butterfly</name>
	<maintenanceCost>1.0</maintenanceCost>
	<dangerPerc>0.0</dangerPerc>
	<takenCareOf>false</takenCareOf>
	<canFly>true</canFly>
	<isDangerous>false</isDangerous>
	<DISCRIMINANT>BUTTERFLY</DISCRIMINANT>
</ANIMAL>
<ANIMAL>
	<nrOfLegs>0</nrOfLegs>
	<name>Shark</name>
	<maintenanceCost>5.2</maintenanceCost>
	<dangerPerc>0.75</dangerPerc>
	<takenCareOf>false</takenCareOf>
	<avgSwimDepth>2000</avgSwimDepth>
	<waterType>SALTWATER</waterType>
	<DISCRIMINANT>SHARK</DISCRIMINANT>
</ANIMAL>
<ANIMAL>
	<nrOfLegs>4</nrOfLegs>
	<name>Lizard</name>
	<maintenanceCost>3.3</maintenanceCost>
	<dangerPerc>0.01</dangerPerc>
	<takenCareOf>false</takenCareOf>
	<layEggs>true</layEggs>
	<DISCRIMINANT>LIZARD</DISCRIMINANT>
</ANIMAL>
<ANIMAL>
	<nrOfLegs>4</nrOfLegs>
	<name>Turtle</name>
	<maintenanceCost>3.9</maintenanceCost>
	<dangerPerc>0.0</dangerPerc>
	<takenCareOf>false</takenCareOf>
	<layEggs>true</layEggs>
	<DISCRIMINANT>TURTLE</DISCRIMINANT>
</ANIMAL>
<ANIMAL>
	<nrOfLegs>4</nrOfLegs>
	<name>Lizard</name>
	<maintenanceCost>3.3</maintenanceCost>
	<dangerPerc>0.01</dangerPerc>
	<takenCareOf>false</takenCareOf>
	<layEggs>true</layEggs>
	<DISCRIMINANT>LIZARD</DISCRIMINANT>
</ANIMAL>
<ANIMAL>
	<nrOfLegs>2</nrOfLegs>
	<name>Owl</name>
	<maintenanceCost>3.6</maintenanceCost>
	<dangerPerc>0.0</dangerPerc>
	<takenCareOf>false</takenCareOf>
	<migrates>false</migrates>
	<avgFlightAltitude>2000</avgFlightAltitude>
	<DISCRIMINANT>OWL</DISCRIMINANT>
</ANIMAL>
<ANIMAL>
	<nrOfLegs>4</nrOfLegs>
	<name>Tiger</name>
	<maintenanceCost>6.3</maintenanceCost>
	<dangerPerc>0.65</dangerPerc>
	<takenCareOf>false</takenCareOf>
	<normalBodyTemp>37.0</normalBodyTemp>
	<percBodyHair>95.3</percBodyHair>
	<DISCRIMINANT>TIGER</DISCRIMINANT>
</ANIMAL>
</content>